mm_203_python_pro/__init__.py
mm_203_python_pro/Interactive_inputs.py
mm_203_python_pro/new_broker.py
mm_203_python_pro/new_data_module.py
mm_203_python_pro/visualizing.py
mm_203_python_pro-0.1.0.dist-info/LICENSE
mm_203_python_pro-0.1.0.dist-info/METADATA
mm_203_python_pro-0.1.0.dist-info/WHEEL
mm_203_python_pro-0.1.0.dist-info/RECORD
