Metadata-Version: 2.3
Name: mm_203_python_pro
Version: 0.1.0
Summary: add functions
License: MIT
Author: Melissa Mesnard
Requires-Python: >=3.12,<4.0
Classifier: License :: OSI Approved :: MIT License
Classifier: Programming Language :: Python :: 3
Classifier: Programming Language :: Python :: 3.12
Classifier: Programming Language :: Python :: 3.13
